README.md
setup.py
turbasen/__init__.py
turbasen/apiclient.py
turbasen/cache.py
turbasen/datatypes.py
turbasen/events.py
turbasen/exceptions.py
turbasen/settings.py
turbasen/util.py
turbasen.egg-info/PKG-INFO
turbasen.egg-info/SOURCES.txt
turbasen.egg-info/dependency_links.txt
turbasen.egg-info/requires.txt
turbasen.egg-info/top_level.txt