Metadata-Version: 1.1
Name: turbasen
Version: 3.2.1
Summary: Client for Nasjonal Turbase REST API
Home-page: https://github.com/Turbasen/turbasen.py
Author: Ali Kaafarani
Author-email: tekno@dnt.no
License: MIT
Download-URL: https://github.com/Turbasen/turbasen.py/tarball/v3.2.1
Keywords: turbasen,nasjonalturbase,turistforening,rest-api
Platform: UNKNOWN
Classifier: Development Status :: 4 - Beta
Classifier: Intended Audience :: Developers
Classifier: License :: OSI Approved :: MIT License
Classifier: Natural Language :: Norwegian
Classifier: Operating System :: OS Independent
Classifier: Programming Language :: Python
Classifier: Programming Language :: Python :: 3
